rnetl/__init__.py
rnetl/datadict.py
rnetl/edge.py
rnetl/experiment.py
rnetl/model.py
rnetl/network.py
rnetl/node.py
rnetl/sample.py
rnetl/version.py
rnetl/visualization.py
rnetl-0.1.0.dist-info/licenses/LICENSE
rnetl-0.1.0.dist-info/METADATA
rnetl-0.1.0.dist-info/WHEEL
rnetl-0.1.0.dist-info/top_level.txt
rnetl-0.1.0.dist-info/RECORD
