Metadata-Version: 2.4
Name: rnetl
Version: 0.1.0
Summary: A package for network logic operations
Home-page: https://github.com/HuaiweiSun/rnetl
Download-URL: https://github.com/HuaiweiSun/rnetl
Author: Huaiwei Sun
Author-email: "Prof. Huaiwei Sun" <hsun@hust.edu.cn>
License-Expression: MIT
Classifier: Programming Language :: Python :: 3
Classifier: Intended Audience :: Science/Research
Classifier: Operating System :: OS Independent
Requires-Python: >=3.9
License-File: LICENSE
Requires-Dist: numpy>=1.18.0
Requires-Dist: pandas>=1.0.0
Requires-Dist: matplotlib>=3.0.0
Requires-Dist: networkx>=2.4
Dynamic: author
Dynamic: download-url
Dynamic: home-page
Dynamic: license-file
